Workbook

Sheet Dashboard
A1: Garden Faery Books
A2: As of April 05, 2026
A4: Year-to-Date Summary
A5: Total Income | B5: =SUM(Income!E2:E201) -> 0
A6: Total Expenses | B6: =SUM(Expenses!C2:C201) -> 0
A7: Net Profit | B7: =B5-B6 -> 0
A9: Total Miles | B9: =SUM(Mileage!D2:D201) -> 0
A10: Mileage Deduction | B10: =SUM(Mileage!F2:F201) -> 0
A11: Best Vehicle Deduction | B11: =Vehicle!B121 -> 0
A13: Total Hours (Garden) | B13: =SUM(Income!C2:C201) -> 0
A14: Total Hours (Admin) | B14: =SUM('Admin Time'!B2:B201) -> 0
A15: Total Visits | B15: =COUNTA(Visits!A2:A201) -> 0
A16: Total Clients | B16: =COUNTA(Clients!A2:A51) -> 0
A18: Estimated SE Tax (15.3%) | B18: =MAX(B7,0)*0.9235*0.153 -> 0
A19: Estimated Income Tax (~12%) | B19: =MAX(B7-Vehicle!B121-12950,0)*0.12 -> 0
A20: Total Estimated Tax | B20: =B18+B19 -> 0
A21: Set Aside per Month | B21: =B20/12 -> 0
A28: Quarterly Tax Due Dates
A29: Q1 | B29: April 15, 2026
A30: Q2 | B30: June 15, 2026
A31: Q3 | B31: September 15, 2026
A32: Q4 | B32: January 15, 2027

Sheet Income
A1: Date | B1: Client | C1: Hours | D1: Rate | E1: Total | F1: Service | G1: Payment | H1: Notes
E2: =IF(C2="","",C2*D2) | G2: Cash
E3: =IF(C3="","",C3*D3) | G3: Cash
E4: =IF(C4="","",C4*D4) | G4: Cash
E5: =IF(C5="","",C5*D5) | G5: Cash
E6: =IF(C6="","",C6*D6) | G6: Cash
E7: =IF(C7="","",C7*D7) | G7: Cash
E8: =IF(C8="","",C8*D8) | G8: Cash
E9: =IF(C9="","",C9*D9) | G9: Cash
E10: =IF(C10="","",C10*D10) | G10: Cash
E11: =IF(C11="","",C11*D11) | G11: Cash
E12: =IF(C12="","",C12*D12) | G12: Cash
E13: =IF(C13="","",C13*D13) | G13: Cash
... E201: =IF(C201="","",C201*D201) | G201: Cash

Sheet Expenses
A1: Date | B1: Vendor | C1: Amount | D1: Category | E1: Description | F1: Receipt? | G1: Truck Expense?

Sheet Mileage
A1: Date | B1: Destination | C1: Purpose | D1: Miles | E1: IRS Rate | F1: Deduction | G1: Notes
E2: 0.7 | F2: =IF(D2="","",D2*E2)
E3: 0.7 | F3: =IF(D3="","",D3*E3)
E4: 0.7 | F4: =IF(D4="","",D4*E4)
E5: 0.7 | F5: =IF(D5="","",D5*E5)
E6: 0.7 | F6: =IF(D6="","",D6*E6)
E7: 0.7 | F7: =IF(D7="","",D7*E7)
E8: 0.7 | F8: =IF(D8="","",D8*E8)
E9: 0.7 | F9: =IF(D9="","",D9*E9)
E10: 0.7 | F10: =IF(D10="","",D10*E10)
E11: 0.7 | F11: =IF(D11="","",D11*E11)
E12: 0.7 | F12: =IF(D12="","",D12*E12)
E13: 0.7 | F13: =IF(D13="","",D13*E13)
... E201: 0.7 | F201: =IF(D201="","",D201*E201)

Sheet Clients
A1: Name | B1: Phone | C1: Email | D1: Address | E1: Round-Trip Miles | F1: Hidy Spot | G1: Last Seen | H1: Notes

Sheet Vehicle
A1: Vehicle Tracking
A3: Current Vehicle:
A4: Year IRS Rate: | B4: 0.7
A6: Odometer Log
A7: Date | B7: Reading | C7: Miles Since Last | D7: Vehicle | E7: Notes
C9: =IF(B9="","",B9-B8)
C10: =IF(B10="","",B10-B9)
C11: =IF(B11="","",B11-B10)
C12: =IF(B12="","",B12-B11)
C13: =IF(B13="","",B13-B12)
C14: =IF(B14="","",B14-B13)
C15: =IF(B15="","",B15-B14)
C16: =IF(B16="","",B16-B15)
C17: =IF(B17="","",B17-B16)
C18: =IF(B18="","",B18-B17)
C19: =IF(B19="","",B19-B18)
C20: =IF(B20="","",B20-B19)
... C107: =IF(B107="","",B107-B106)
A110: Deduction Comparison (Annual)
A112: Standard Mileage Method
A113: Total Miles Driven: | B113: =SUM(Mileage!D2:D201) -> 0
A114: IRS Rate: | B114: =B4 -> 0.7
A115: Standard Deduction: | B115: =B113*B114 -> 0
A117: Actual Expense Method
A118: Truck Expenses: | B118: =SUMPRODUCT((Expenses!G2:G201="Yes")*(Expenses!C2:C201)) -> 0
A119: Actual Deduction: | B119: =B118 -> 0
A121: BEST DEDUCTION: | B121: =MAX(B115,B119) -> 0
A122: Method: | B122: =IF(B115>=B119,"Standard Mileage","Actual Expenses") -> Standard Mileage

Sheet Admin Time
A1: Date | B1: Hours | C1: Rate | D1: Total | E1: Category | F1: Notes
C2: 25 | D2: =IF(B2="","",B2*C2)
C3: 25 | D3: =IF(B3="","",B3*C3)
C4: 25 | D4: =IF(B4="","",B4*C4)
C5: 25 | D5: =IF(B5="","",B5*C5)
C6: 25 | D6: =IF(B6="","",B6*C6)
C7: 25 | D7: =IF(B7="","",B7*C7)
C8: 25 | D8: =IF(B8="","",B8*C8)
C9: 25 | D9: =IF(B9="","",B9*C9)
C10: 25 | D10: =IF(B10="","",B10*C10)
C11: 25 | D11: =IF(B11="","",B11*C11)
C12: 25 | D12: =IF(B12="","",B12*C12)
C13: 25 | D13: =IF(B13="","",B13*C13)
... C201: 25 | D201: =IF(B201="","",B201*C201)

Sheet Visits
A1: Date | B1: Client | C1: Hours | D1: Tasks | E1: Schedule | F1: Notes
